{
  "version": "1",
  "metadata": {
    "marimo_version": "0.23.13",
    "script_metadata_hash": null
  },
  "cells": [
    {
      "id": "Hbol",
      "code_hash": "db87d2708ec2d873ffe91ef2f09520cb",
      "outputs": [
        {
          "type": "error",
          "ename": "syntax",
          "evalue": "line 2\n    import \"build/Algorithms.cpython-314-x86_64-linux-gnu.so\" as alg\n           ^^^^^^^^^^^^^^^^^^^^^^^^^^^^^^^^^^^^^^^^^^^^^^^^^^\nSyntaxError: invalid syntax\n",
          "traceback": []
        }
      ],
      "console": []
    },
    {
      "id": "fmNZ",
      "code_hash": null,
      "outputs": [],
      "console": []
    }
  ]
}